spacenav_ws/__init__.py
spacenav_ws/controller.py
spacenav_ws/main.py
spacenav_ws/spacenav.py
spacenav_ws/wamp.py
spacenav_ws/certs/ip.cnf
spacenav_ws/certs/ip.crt
spacenav_ws/certs/ip.csr
spacenav_ws/certs/ip.key
spacenav_ws-0.1.5.dist-info/METADATA
spacenav_ws-0.1.5.dist-info/WHEEL
spacenav_ws-0.1.5.dist-info/entry_points.txt
spacenav_ws-0.1.5.dist-info/licenses/LICENSE
spacenav_ws-0.1.5.dist-info/RECORD
